ctenv/LICENSE-gosu
ctenv/__init__.py
ctenv/__main__.py
ctenv/cli.py
ctenv/config.py
ctenv/container.py
ctenv/image.py
ctenv/version.py
ctenv/binaries/__init__.py
ctenv/binaries/gosu-amd64
ctenv/binaries/gosu-arm64
ctenv-0.12.dist-info/licenses/LICENSE
ctenv-0.12.dist-info/licenses/NOTICE
ctenv-0.12.dist-info/METADATA
ctenv-0.12.dist-info/WHEEL
ctenv-0.12.dist-info/entry_points.txt
ctenv-0.12.dist-info/top_level.txt
ctenv-0.12.dist-info/RECORD
