Metadata-Version: 2.4
Name: ctenv
Version: 0.12
Summary: ctenv is a tool for running in containers as current user
Author-email: Oskar Skoog <oskar@osd.se>
License-Expression: Apache-2.0
Project-URL: Homepage, https://github.com/osks/ctenv
Project-URL: Changelog, https://github.com/osks/ctenv/releases
Project-URL: Issues, https://github.com/osks/ctenv/issues
Project-URL: CI, https://github.com/osks/ctenv/actions
Requires-Python: >=3.10
License-File: LICENSE
License-File: NOTICE
Requires-Dist: tomli; python_version < "3.11"
Provides-Extra: test
Requires-Dist: pytest; extra == "test"
Requires-Dist: pytest-mock; extra == "test"
Requires-Dist: pytest-cov; extra == "test"
Requires-Dist: ruff; extra == "test"
Requires-Dist: mypy; extra == "test"
Requires-Dist: tox>=4.27.0; extra == "test"
Requires-Dist: tox-uv>=1.26.1; extra == "test"
Provides-Extra: dev
Requires-Dist: build>=1.2.2.post1; extra == "dev"
Dynamic: license-file
